{
  "ComponentIndexes": {},
  "ControlUniqueGuids": {},
  "ControlUniqueIds": {
    "App": 1,
    "Attachments_DataCard1": 375,
    "Background Dim": 385,
    "Bill To Customer #_DataCard1": 45,
    "ComboBox1": 83,
    "Completed Button": 387,
    "Completed Serial Cards": 383,
    "Create Button": 386,
    "Customer PO #_DataCard1": 30,
    "DataCardKey11": 42,
    "DataCardKey12": 47,
    "DataCardKey13": 52,
    "DataCardKey15": 72,
    "DataCardKey16": 77,
    "DataCardKey17": 82,
    "DataCardKey18": 87,
    "DataCardKey19": 92,
    "DataCardKey20": 97,
    "DataCardKey21": 102,
    "DataCardKey22": 107,
    "DataCardKey23": 112,
    "DataCardKey24": 117,
    "DataCardKey25": 122,
    "DataCardKey26": 127,
    "DataCardKey27": 132,
    "DataCardKey28": 137,
    "DataCardKey29": 142,
    "DataCardKey3": 12,
    "DataCardKey30": 147,
    "DataCardKey31": 152,
    "DataCardKey32": 157,
    "DataCardKey33": 162,
    "DataCardKey34": 167,
    "DataCardKey35": 182,
    "DataCardKey36": 172,
    "DataCardKey37": 177,
    "DataCardKey38": 207,
    "DataCardKey39": 187,
    "DataCardKey4": 17,
    "DataCardKey40": 192,
    "DataCardKey41": 222,
    "DataCardKey42": 197,
    "DataCardKey43": 202,
    "DataCardKey44": 237,
    "DataCardKey45": 212,
    "DataCardKey46": 217,
    "DataCardKey47": 252,
    "DataCardKey48": 227,
    "DataCardKey5": 7,
    "DataCardKey50": 247,
    "DataCardKey52": 267,
    "DataCardKey55": 62,
    "DataCardKey56": 67,
    "DataCardKey57": 57,
    "DataCardKey58": 282,
    "DataCardKey59": 272,
    "DataCardKey6": 22,
    "DataCardKey60": 277,
    "DataCardKey61": 297,
    "DataCardKey62": 287,
    "DataCardKey63": 292,
    "DataCardKey64": 307,
    "DataCardKey65": 312,
    "DataCardKey66": 302,
    "DataCardKey67": 322,
    "DataCardKey68": 327,
    "DataCardKey69": 317,
    "DataCardKey7": 27,
    "DataCardKey70": 337,
    "DataCardKey71": 342,
    "DataCardKey72": 332,
    "DataCardKey73": 357,
    "DataCardKey74": 347,
    "DataCardKey75": 352,
    "DataCardKey76": 372,
    "DataCardKey77": 362,
    "DataCardKey78": 367,
    "DataCardKey79": 377,
    "DataCardKey8": 32,
    "DataCardKey9": 37,
    "DataCardValue1": 13,
    "DataCardValue10": 48,
    "DataCardValue11": 53,
    "DataCardValue13": 73,
    "DataCardValue14": 78,
    "DataCardValue16": 88,
    "DataCardValue17": 93,
    "DataCardValue18": 98,
    "DataCardValue19": 103,
    "DataCardValue2": 18,
    "DataCardValue20": 108,
    "DataCardValue21": 113,
    "DataCardValue22": 118,
    "DataCardValue23": 123,
    "DataCardValue24": 128,
    "DataCardValue25": 133,
    "DataCardValue26": 138,
    "DataCardValue27": 143,
    "DataCardValue28": 148,
    "DataCardValue29": 153,
    "DataCardValue3": 8,
    "DataCardValue30": 158,
    "DataCardValue31": 163,
    "DataCardValue32": 168,
    "DataCardValue33": 183,
    "DataCardValue34": 173,
    "DataCardValue35": 178,
    "DataCardValue36": 208,
    "DataCardValue37": 188,
    "DataCardValue38": 193,
    "DataCardValue39": 223,
    "DataCardValue4": 23,
    "DataCardValue40": 198,
    "DataCardValue41": 203,
    "DataCardValue42": 238,
    "DataCardValue43": 213,
    "DataCardValue44": 218,
    "DataCardValue45": 253,
    "DataCardValue46": 228,
    "DataCardValue48": 248,
    "DataCardValue5": 28,
    "DataCardValue53": 63,
    "DataCardValue54": 68,
    "DataCardValue55": 58,
    "DataCardValue56": 283,
    "DataCardValue57": 273,
    "DataCardValue58": 278,
    "DataCardValue59": 298,
    "DataCardValue6": 33,
    "DataCardValue60": 288,
    "DataCardValue61": 293,
    "DataCardValue62": 308,
    "DataCardValue63": 313,
    "DataCardValue64": 303,
    "DataCardValue65": 323,
    "DataCardValue66": 328,
    "DataCardValue67": 318,
    "DataCardValue68": 338,
    "DataCardValue69": 343,
    "DataCardValue7": 38,
    "DataCardValue70": 333,
    "DataCardValue71": 358,
    "DataCardValue72": 348,
    "DataCardValue73": 353,
    "DataCardValue74": 373,
    "DataCardValue75": 363,
    "DataCardValue76": 368,
    "DataCardValue77": 378,
    "DataCardValue9": 43,
    "DatePicker2": 389,
    "EM String(s) for Product (A)_DataCard1": 75,
    "EM String(s) for Product (B)_DataCard1": 90,
    "EM String(s) for Product (C)_DataCard1": 105,
    "EM String(s) for Product (D)_DataCard1": 120,
    "EM String(s) for Product (E)_DataCard1": 135,
    "EM String(s) for Product (F)_DataCard1": 150,
    "EM String(s) for Product (G)_DataCard1": 165,
    "EM String(s) for Product (H)_DataCard1": 175,
    "EM String(s) for Product (I)_DataCard1": 190,
    "EM String(s) for Product (J)_DataCard1": 200,
    "Email_DataCard1": 10,
    "End Serial #_DataCard1": 250,
    "ErrorMessage11": 44,
    "ErrorMessage12": 49,
    "ErrorMessage13": 54,
    "ErrorMessage15": 74,
    "ErrorMessage16": 79,
    "ErrorMessage17": 84,
    "ErrorMessage18": 89,
    "ErrorMessage19": 94,
    "ErrorMessage20": 99,
    "ErrorMessage21": 104,
    "ErrorMessage22": 109,
    "ErrorMessage23": 114,
    "ErrorMessage24": 119,
    "ErrorMessage25": 124,
    "ErrorMessage26": 129,
    "ErrorMessage27": 134,
    "ErrorMessage28": 139,
    "ErrorMessage29": 144,
    "ErrorMessage3": 14,
    "ErrorMessage30": 149,
    "ErrorMessage31": 154,
    "ErrorMessage32": 159,
    "ErrorMessage33": 164,
    "ErrorMessage34": 169,
    "ErrorMessage35": 184,
    "ErrorMessage36": 174,
    "ErrorMessage37": 179,
    "ErrorMessage38": 209,
    "ErrorMessage39": 189,
    "ErrorMessage4": 19,
    "ErrorMessage40": 194,
    "ErrorMessage41": 224,
    "ErrorMessage42": 199,
    "ErrorMessage43": 204,
    "ErrorMessage44": 239,
    "ErrorMessage45": 214,
    "ErrorMessage46": 219,
    "ErrorMessage47": 254,
    "ErrorMessage48": 229,
    "ErrorMessage5": 9,
    "ErrorMessage50": 249,
    "ErrorMessage52": 269,
    "ErrorMessage55": 64,
    "ErrorMessage56": 69,
    "ErrorMessage57": 59,
    "ErrorMessage58": 284,
    "ErrorMessage59": 274,
    "ErrorMessage6": 24,
    "ErrorMessage60": 279,
    "ErrorMessage61": 299,
    "ErrorMessage62": 289,
    "ErrorMessage63": 294,
    "ErrorMessage64": 309,
    "ErrorMessage65": 314,
    "ErrorMessage66": 304,
    "ErrorMessage67": 324,
    "ErrorMessage68": 329,
    "ErrorMessage69": 319,
    "ErrorMessage7": 29,
    "ErrorMessage70": 339,
    "ErrorMessage71": 344,
    "ErrorMessage72": 334,
    "ErrorMessage73": 359,
    "ErrorMessage74": 349,
    "ErrorMessage75": 354,
    "ErrorMessage76": 374,
    "ErrorMessage77": 364,
    "ErrorMessage78": 369,
    "ErrorMessage79": 379,
    "ErrorMessage8": 34,
    "ErrorMessage9": 39,
    "Form1": 4,
    "Gaby Test Screen": 380,
    "Home Screen": 384,
    "Is this a range of Serial Numbers?_DataCard1": 215,
    "LBP Order #_DataCard1": 25,
    "Name (field_4)_DataCard1": 15,
    "Oracle Line #_DataCard1": 35,
    "Order Date_DataCard1": 265,
    "Order Qty_DataCard1": 245,
    "Please add configured Item Number_DataCard1": 235,
    "Please add the Tag Number_DataCard1": 280,
    "Please Enter Special Note Value\u00A0(A)_DataCard1": 270,
    "Please Enter Special Note Value\u00A0(B)_DataCard1": 335,
    "Please Enter Special Note Value\u00A0(C)_DataCard1": 340,
    "Please Enter Special Note Value\u00A0(D)_DataCard1": 330,
    "Please Enter Special Note Value\u00A0(E)_DataCard1": 355,
    "Please Enter Special Note Value\u00A0(F)_DataCard1": 345,
    "Please Enter Special Note Value\u00A0(G)_DataCard1": 350,
    "Please Enter Special Note Value\u00A0(H)_DataCard1": 370,
    "Please Enter Special Note Value\u00A0(I)_DataCard1": 360,
    "Please Enter Special Note Value\u00A0(J)_DataCard1": 365,
    "Please enter the Current Location Number_DataCard1": 60,
    "Please enter the Installed At Number_DataCard1": 65,
    "Please Select Note Type\u00A0(A)_DataCard1": 275,
    "Please Select Note Type\u00A0(B)_DataCard1": 305,
    "Please Select Note Type\u00A0(C)_DataCard1": 290,
    "Please Select Note Type\u00A0(D)_DataCard1": 315,
    "Please Select Note Type\u00A0(E)_DataCard1": 300,
    "Please Select Note Type\u00A0(F)_DataCard1": 310,
    "Please Select Note Type\u00A0(G)_DataCard1": 320,
    "Please Select Note Type\u00A0(H)_DataCard1": 325,
    "Please Select Note Type\u00A0(I)_DataCard1": 295,
    "Please Select Note Type\u00A0(J)_DataCard1": 285,
    "Please select the Organization Code below_DataCard1": 20,
    "Product # (A)_DataCard1": 70,
    "Product # (B)_DataCard1": 85,
    "Product # (C)_DataCard1": 100,
    "Product # (D)_DataCard1": 115,
    "Product # (E)_DataCard1": 130,
    "Product # (F)_DataCard1": 145,
    "Product # (G)_DataCard1": 160,
    "Product # (H)_DataCard1": 170,
    "Product # (I)_DataCard1": 185,
    "Product # (J)_DataCard1": 195,
    "Product (B) Y/N_DataCard1": 80,
    "Product (C) Y/N_DataCard1": 95,
    "Product (D) Y/N_DataCard1": 110,
    "Product (E) Y/N_DataCard1": 125,
    "Product (F) Y/N_DataCard1": 140,
    "Product (G) Y/N_DataCard1": 155,
    "Product (H) Y/N_DataCard1": 180,
    "Product (I) Y/N_DataCard1": 205,
    "Product (J) Y/N_DataCard1": 220,
    "Repair #_DataCard1": 225,
    "Sales Person Name_DataCard1": 40,
    "Serial #_DataCard1": 210,
    "Serial Card Request Screen": 3,
    "Ship To Customer #_DataCard1": 50,
    "Ship To Customer Address the same as Current Location and Installed At?_DataCard1": 55,
    "StarVisible11": 41,
    "StarVisible12": 46,
    "StarVisible13": 51,
    "StarVisible15": 71,
    "StarVisible16": 76,
    "StarVisible17": 81,
    "StarVisible18": 86,
    "StarVisible19": 91,
    "StarVisible20": 96,
    "StarVisible21": 101,
    "StarVisible22": 106,
    "StarVisible23": 111,
    "StarVisible24": 116,
    "StarVisible25": 121,
    "StarVisible26": 126,
    "StarVisible27": 131,
    "StarVisible28": 136,
    "StarVisible29": 141,
    "StarVisible3": 11,
    "StarVisible30": 146,
    "StarVisible31": 151,
    "StarVisible32": 156,
    "StarVisible33": 161,
    "StarVisible34": 166,
    "StarVisible35": 181,
    "StarVisible36": 171,
    "StarVisible37": 176,
    "StarVisible38": 206,
    "StarVisible39": 186,
    "StarVisible4": 16,
    "StarVisible40": 191,
    "StarVisible41": 221,
    "StarVisible42": 196,
    "StarVisible43": 201,
    "StarVisible44": 236,
    "StarVisible45": 211,
    "StarVisible46": 216,
    "StarVisible47": 251,
    "StarVisible48": 226,
    "StarVisible5": 6,
    "StarVisible50": 246,
    "StarVisible52": 266,
    "StarVisible55": 61,
    "StarVisible56": 66,
    "StarVisible57": 56,
    "StarVisible58": 281,
    "StarVisible59": 271,
    "StarVisible6": 21,
    "StarVisible60": 276,
    "StarVisible61": 296,
    "StarVisible62": 286,
    "StarVisible63": 291,
    "StarVisible64": 306,
    "StarVisible65": 311,
    "StarVisible66": 301,
    "StarVisible67": 321,
    "StarVisible68": 326,
    "StarVisible69": 316,
    "StarVisible7": 26,
    "StarVisible70": 336,
    "StarVisible71": 341,
    "StarVisible72": 331,
    "StarVisible73": 356,
    "StarVisible74": 346,
    "StarVisible75": 351,
    "StarVisible76": 371,
    "StarVisible77": 361,
    "StarVisible78": 366,
    "StarVisible79": 376,
    "StarVisible8": 31,
    "StarVisible9": 36,
    "TextInput2": 382,
    "Toggle1": 381,
    "User Name_DataCard1": 5
  },
  "FunctionParamsInvariantScripts": {},
  "FunctionParamsInvariantScriptsOnInstances": {},
  "HeaderLastSavedDateTimeUTC": "01/03/2023 19:57:37",
  "IsLegacyComponentAllowGlobalScopeCase": false,
  "LocalConnectionIDReferences": {
    "4c94acaa-2b52-4fba-bf4f-ec5ae1521514": "\"/providers/microsoft.powerapps/apis/shared_office365users/connections/bffa72a5c03e43ffac064ff184193b90\"",
    "f9a0fc89-e3d1-4412-b890-0787dba129e0": "\"/providers/microsoft.powerapps/apis/shared_sharepointonline/connections/aec37ddcc97e4537aa5723c1362a8fdd\""
  },
  "LocalDatabaseReferencesAsEmpty": false,
  "LocalResourceFileNames": {
    "warehouse-worker-checking-orders-at-computer": "0001.jpg"
  },
  "LocalResourceRootPaths": {
    "warehouse-worker-checking-orders-at-computer": "https://docserverpwaprodeus.blob.core.windows.net/718a09b3-cbd2-4adf-95c3-3c8df08bcb14-1/resource/Assets0Images00001.jpg?sv=2017-04-17&sr=b&sig=VAHTW%2BUpNURpqYk4SuaQxDHzLTOxcd1lshR%2BLSLcK9k%3D&spr=https&se=2023-01-04T19%3A10%3A40Z&sp=r"
  },
  "OrderComponentMetadata": {},
  "OrderComponentTemplate": {},
  "OrderDataSource": {
    "ComboBoxSample": 3,
    "CustomGallerySample": 1,
    "DropDownSample": 4,
    "Form Response Collection": 2,
    "Office365Users": 0
  },
  "OrderGroupControls": {},
  "OrderPcfTemplate": {},
  "OrderTemplate": {},
  "OrderXMLTemplate": {
    "attachments": 5,
    "button": 8,
    "combobox": 3,
    "datepicker": 4,
    "form": 0,
    "label": 1,
    "rectangle": 7,
    "text": 2,
    "toggleSwitch": 6
  },
  "PublishOrderIndices": {
    "App": 0,
    "Attachments_DataCard1": 354,
    "Background Dim": 0,
    "Bill To Customer #_DataCard1": 44,
    "ComboBox1": 92,
    "Completed Button": 2,
    "Completed Serial Cards": 2,
    "Create Button": 1,
    "Customer PO #_DataCard1": 29,
    "DataCardKey11": 41,
    "DataCardKey12": 46,
    "DataCardKey13": 51,
    "DataCardKey15": 71,
    "DataCardKey16": 76,
    "DataCardKey17": 91,
    "DataCardKey18": 96,
    "DataCardKey19": 101,
    "DataCardKey20": 116,
    "DataCardKey21": 121,
    "DataCardKey22": 126,
    "DataCardKey23": 141,
    "DataCardKey24": 146,
    "DataCardKey25": 151,
    "DataCardKey26": 166,
    "DataCardKey27": 171,
    "DataCardKey28": 176,
    "DataCardKey29": 191,
    "DataCardKey3": 11,
    "DataCardKey30": 196,
    "DataCardKey31": 201,
    "DataCardKey32": 216,
    "DataCardKey33": 221,
    "DataCardKey34": 226,
    "DataCardKey35": 241,
    "DataCardKey36": 246,
    "DataCardKey37": 251,
    "DataCardKey38": 266,
    "DataCardKey39": 271,
    "DataCardKey4": 16,
    "DataCardKey40": 276,
    "DataCardKey41": 291,
    "DataCardKey42": 296,
    "DataCardKey43": 301,
    "DataCardKey44": 316,
    "DataCardKey45": 321,
    "DataCardKey46": 326,
    "DataCardKey47": 331,
    "DataCardKey48": 341,
    "DataCardKey5": 6,
    "DataCardKey50": 346,
    "DataCardKey52": 351,
    "DataCardKey55": 61,
    "DataCardKey56": 66,
    "DataCardKey57": 56,
    "DataCardKey58": 336,
    "DataCardKey59": 86,
    "DataCardKey6": 21,
    "DataCardKey60": 81,
    "DataCardKey61": 281,
    "DataCardKey62": 306,
    "DataCardKey63": 131,
    "DataCardKey64": 106,
    "DataCardKey65": 206,
    "DataCardKey66": 181,
    "DataCardKey67": 231,
    "DataCardKey68": 256,
    "DataCardKey69": 156,
    "DataCardKey7": 26,
    "DataCardKey70": 111,
    "DataCardKey71": 136,
    "DataCardKey72": 161,
    "DataCardKey73": 186,
    "DataCardKey74": 211,
    "DataCardKey75": 236,
    "DataCardKey76": 261,
    "DataCardKey77": 286,
    "DataCardKey78": 311,
    "DataCardKey79": 356,
    "DataCardKey8": 31,
    "DataCardKey9": 36,
    "DataCardValue1": 12,
    "DataCardValue10": 47,
    "DataCardValue11": 52,
    "DataCardValue13": 72,
    "DataCardValue14": 77,
    "DataCardValue16": 97,
    "DataCardValue17": 102,
    "DataCardValue18": 117,
    "DataCardValue19": 122,
    "DataCardValue2": 17,
    "DataCardValue20": 127,
    "DataCardValue21": 142,
    "DataCardValue22": 147,
    "DataCardValue23": 152,
    "DataCardValue24": 167,
    "DataCardValue25": 172,
    "DataCardValue26": 177,
    "DataCardValue27": 192,
    "DataCardValue28": 197,
    "DataCardValue29": 202,
    "DataCardValue3": 7,
    "DataCardValue30": 217,
    "DataCardValue31": 222,
    "DataCardValue32": 227,
    "DataCardValue33": 242,
    "DataCardValue34": 247,
    "DataCardValue35": 252,
    "DataCardValue36": 267,
    "DataCardValue37": 272,
    "DataCardValue38": 277,
    "DataCardValue39": 292,
    "DataCardValue4": 22,
    "DataCardValue40": 297,
    "DataCardValue41": 302,
    "DataCardValue42": 317,
    "DataCardValue43": 322,
    "DataCardValue44": 327,
    "DataCardValue45": 332,
    "DataCardValue46": 342,
    "DataCardValue48": 347,
    "DataCardValue5": 27,
    "DataCardValue53": 62,
    "DataCardValue54": 67,
    "DataCardValue55": 57,
    "DataCardValue56": 337,
    "DataCardValue57": 87,
    "DataCardValue58": 82,
    "DataCardValue59": 282,
    "DataCardValue6": 32,
    "DataCardValue60": 307,
    "DataCardValue61": 132,
    "DataCardValue62": 107,
    "DataCardValue63": 207,
    "DataCardValue64": 182,
    "DataCardValue65": 232,
    "DataCardValue66": 257,
    "DataCardValue67": 157,
    "DataCardValue68": 112,
    "DataCardValue69": 137,
    "DataCardValue7": 37,
    "DataCardValue70": 162,
    "DataCardValue71": 187,
    "DataCardValue72": 212,
    "DataCardValue73": 237,
    "DataCardValue74": 262,
    "DataCardValue75": 287,
    "DataCardValue76": 312,
    "DataCardValue77": 357,
    "DataCardValue9": 42,
    "DatePicker2": 352,
    "EM String(s) for Product (A)_DataCard1": 74,
    "EM String(s) for Product (B)_DataCard1": 99,
    "EM String(s) for Product (C)_DataCard1": 124,
    "EM String(s) for Product (D)_DataCard1": 149,
    "EM String(s) for Product (E)_DataCard1": 174,
    "EM String(s) for Product (F)_DataCard1": 199,
    "EM String(s) for Product (G)_DataCard1": 224,
    "EM String(s) for Product (H)_DataCard1": 249,
    "EM String(s) for Product (I)_DataCard1": 274,
    "EM String(s) for Product (J)_DataCard1": 299,
    "Email_DataCard1": 9,
    "End Serial #_DataCard1": 329,
    "ErrorMessage11": 43,
    "ErrorMessage12": 48,
    "ErrorMessage13": 53,
    "ErrorMessage15": 73,
    "ErrorMessage16": 78,
    "ErrorMessage17": 93,
    "ErrorMessage18": 98,
    "ErrorMessage19": 103,
    "ErrorMessage20": 118,
    "ErrorMessage21": 123,
    "ErrorMessage22": 128,
    "ErrorMessage23": 143,
    "ErrorMessage24": 148,
    "ErrorMessage25": 153,
    "ErrorMessage26": 168,
    "ErrorMessage27": 173,
    "ErrorMessage28": 178,
    "ErrorMessage29": 193,
    "ErrorMessage3": 13,
    "ErrorMessage30": 198,
    "ErrorMessage31": 203,
    "ErrorMessage32": 218,
    "ErrorMessage33": 223,
    "ErrorMessage34": 228,
    "ErrorMessage35": 243,
    "ErrorMessage36": 248,
    "ErrorMessage37": 253,
    "ErrorMessage38": 268,
    "ErrorMessage39": 273,
    "ErrorMessage4": 18,
    "ErrorMessage40": 278,
    "ErrorMessage41": 293,
    "ErrorMessage42": 298,
    "ErrorMessage43": 303,
    "ErrorMessage44": 318,
    "ErrorMessage45": 323,
    "ErrorMessage46": 328,
    "ErrorMessage47": 333,
    "ErrorMessage48": 343,
    "ErrorMessage5": 8,
    "ErrorMessage50": 348,
    "ErrorMessage52": 353,
    "ErrorMessage55": 63,
    "ErrorMessage56": 68,
    "ErrorMessage57": 58,
    "ErrorMessage58": 338,
    "ErrorMessage59": 88,
    "ErrorMessage6": 23,
    "ErrorMessage60": 83,
    "ErrorMessage61": 283,
    "ErrorMessage62": 308,
    "ErrorMessage63": 133,
    "ErrorMessage64": 108,
    "ErrorMessage65": 208,
    "ErrorMessage66": 183,
    "ErrorMessage67": 233,
    "ErrorMessage68": 258,
    "ErrorMessage69": 158,
    "ErrorMessage7": 28,
    "ErrorMessage70": 113,
    "ErrorMessage71": 138,
    "ErrorMessage72": 163,
    "ErrorMessage73": 188,
    "ErrorMessage74": 213,
    "ErrorMessage75": 238,
    "ErrorMessage76": 263,
    "ErrorMessage77": 288,
    "ErrorMessage78": 313,
    "ErrorMessage79": 358,
    "ErrorMessage8": 33,
    "ErrorMessage9": 38,
    "Form1": 3,
    "Gaby Test Screen": 0,
    "Home Screen": 3,
    "Is this a range of Serial Numbers?_DataCard1": 324,
    "LBP Order #_DataCard1": 24,
    "Name (field_4)_DataCard1": 14,
    "Oracle Line #_DataCard1": 34,
    "Order Date_DataCard1": 349,
    "Order Qty_DataCard1": 344,
    "Please add configured Item Number_DataCard1": 314,
    "Please add the Tag Number_DataCard1": 334,
    "Please Enter Special Note Value\u00A0(A)_DataCard1": 84,
    "Please Enter Special Note Value\u00A0(B)_DataCard1": 109,
    "Please Enter Special Note Value\u00A0(C)_DataCard1": 134,
    "Please Enter Special Note Value\u00A0(D)_DataCard1": 159,
    "Please Enter Special Note Value\u00A0(E)_DataCard1": 184,
    "Please Enter Special Note Value\u00A0(F)_DataCard1": 209,
    "Please Enter Special Note Value\u00A0(G)_DataCard1": 234,
    "Please Enter Special Note Value\u00A0(H)_DataCard1": 259,
    "Please Enter Special Note Value\u00A0(I)_DataCard1": 284,
    "Please Enter Special Note Value\u00A0(J)_DataCard1": 309,
    "Please enter the Current Location Number_DataCard1": 59,
    "Please enter the Installed At Number_DataCard1": 64,
    "Please Select Note Type\u00A0(A)_DataCard1": 79,
    "Please Select Note Type\u00A0(B)_DataCard1": 104,
    "Please Select Note Type\u00A0(C)_DataCard1": 129,
    "Please Select Note Type\u00A0(D)_DataCard1": 154,
    "Please Select Note Type\u00A0(E)_DataCard1": 179,
    "Please Select Note Type\u00A0(F)_DataCard1": 204,
    "Please Select Note Type\u00A0(G)_DataCard1": 229,
    "Please Select Note Type\u00A0(H)_DataCard1": 254,
    "Please Select Note Type\u00A0(I)_DataCard1": 279,
    "Please Select Note Type\u00A0(J)_DataCard1": 304,
    "Please select the Organization Code below_DataCard1": 19,
    "Product # (A)_DataCard1": 69,
    "Product # (B)_DataCard1": 94,
    "Product # (C)_DataCard1": 119,
    "Product # (D)_DataCard1": 144,
    "Product # (E)_DataCard1": 169,
    "Product # (F)_DataCard1": 194,
    "Product # (G)_DataCard1": 219,
    "Product # (H)_DataCard1": 244,
    "Product # (I)_DataCard1": 269,
    "Product # (J)_DataCard1": 294,
    "Product (B) Y/N_DataCard1": 89,
    "Product (C) Y/N_DataCard1": 114,
    "Product (D) Y/N_DataCard1": 139,
    "Product (E) Y/N_DataCard1": 164,
    "Product (F) Y/N_DataCard1": 189,
    "Product (G) Y/N_DataCard1": 214,
    "Product (H) Y/N_DataCard1": 239,
    "Product (I) Y/N_DataCard1": 264,
    "Product (J) Y/N_DataCard1": 289,
    "Repair #_DataCard1": 339,
    "Sales Person Name_DataCard1": 39,
    "Serial #_DataCard1": 319,
    "Serial Card Request Screen": 7,
    "Ship To Customer #_DataCard1": 49,
    "Ship To Customer Address the same as Current Location and Installed At?_DataCard1": 54,
    "StarVisible11": 40,
    "StarVisible12": 45,
    "StarVisible13": 50,
    "StarVisible15": 70,
    "StarVisible16": 75,
    "StarVisible17": 90,
    "StarVisible18": 95,
    "StarVisible19": 100,
    "StarVisible20": 115,
    "StarVisible21": 120,
    "StarVisible22": 125,
    "StarVisible23": 140,
    "StarVisible24": 145,
    "StarVisible25": 150,
    "StarVisible26": 165,
    "StarVisible27": 170,
    "StarVisible28": 175,
    "StarVisible29": 190,
    "StarVisible3": 10,
    "StarVisible30": 195,
    "StarVisible31": 200,
    "StarVisible32": 215,
    "StarVisible33": 220,
    "StarVisible34": 225,
    "StarVisible35": 240,
    "StarVisible36": 245,
    "StarVisible37": 250,
    "StarVisible38": 265,
    "StarVisible39": 270,
    "StarVisible4": 15,
    "StarVisible40": 275,
    "StarVisible41": 290,
    "StarVisible42": 295,
    "StarVisible43": 300,
    "StarVisible44": 315,
    "StarVisible45": 320,
    "StarVisible46": 325,
    "StarVisible47": 330,
    "StarVisible48": 340,
    "StarVisible5": 5,
    "StarVisible50": 345,
    "StarVisible52": 350,
    "StarVisible55": 60,
    "StarVisible56": 65,
    "StarVisible57": 55,
    "StarVisible58": 335,
    "StarVisible59": 85,
    "StarVisible6": 20,
    "StarVisible60": 80,
    "StarVisible61": 280,
    "StarVisible62": 305,
    "StarVisible63": 130,
    "StarVisible64": 105,
    "StarVisible65": 205,
    "StarVisible66": 180,
    "StarVisible67": 230,
    "StarVisible68": 255,
    "StarVisible69": 155,
    "StarVisible7": 25,
    "StarVisible70": 110,
    "StarVisible71": 135,
    "StarVisible72": 160,
    "StarVisible73": 185,
    "StarVisible74": 210,
    "StarVisible75": 235,
    "StarVisible76": 260,
    "StarVisible77": 285,
    "StarVisible78": 310,
    "StarVisible79": 355,
    "StarVisible8": 30,
    "StarVisible9": 35,
    "TextInput2": 360,
    "Toggle1": 359,
    "User Name_DataCard1": 4
  },
  "ResourcesJsonIndices": {
    "Image-SampleImage": 0,
    "Image-warehouse-worker-checking-orders-at-computer": 1
  },
  "RuleScreenIdWithoutScreen": {},
  "TemplateVersions": {},
  "VolatileProperties": {
    "AnalysisLoadTime": 7.4331608,
    "ControlCount": {
      "attachments": 1,
      "button": 2,
      "combobox": 21,
      "form": 1,
      "label": 225,
      "rectangle": 1,
      "screen": 4,
      "text": 54,
      "toggleSwitch": 1,
      "typedDataCard": 75
    },
    "DeserializationLoadTime": 6.229444,
    "ErrorCount": 0
  },
  "WasLocalDatabaseReferencesEmpty": true
}